{
  "id" : "PTX4GP37",
  "name" : "登录",
  "description" : "",
  "parameters" : [ {
    "id" : "KKBC43QA",
    "name" : "userName",
    "dataType" : {
      "typeId" : "String"
    },
    "isRequired" : true
  }, {
    "id" : "FA17U88C",
    "name" : "password",
    "dataType" : {
      "typeId" : "String"
    },
    "isRequired" : true
  }, {
    "id" : "MG1HGZIE",
    "name" : "rememberMe",
    "dataType" : {
      "typeId" : "Boolean"
    },
    "defaultValue" : {
      "type" : "literal",
      "literal" : "false"
    },
    "isRequired" : true
  } ],
  "variables" : [ ],
  "returnValues" : [ {
    "id" : "Z93633WO",
    "name" : "message",
    "dataType" : {
      "typeId" : "String"
    },
    "defaultValue" : {
      "type" : "literal",
      "literal" : ""
    }
  }, {
    "id" : "QGIBPXNE",
    "name" : "success",
    "dataType" : {
      "typeId" : "Boolean"
    },
    "defaultValue" : {
      "type" : "literal",
      "literal" : ""
    }
  } ]
}